freq_table/__init__.py
freq_table/__main__.py
freq_table/cli.py
freq_table/generator.py
freq_table/records.py
freq_table/scraper.py
freq_table/utils.py
freq_table/templates/config.yaml
freq_table/templates/output.html.mako
freq_table/templates/records.yaml
freq_table/templates/style.css
freq_table-0.2.2.dist-info/LICENSE
freq_table-0.2.2.dist-info/METADATA
freq_table-0.2.2.dist-info/WHEEL
freq_table-0.2.2.dist-info/entry_points.txt
freq_table-0.2.2.dist-info/top_level.txt
freq_table-0.2.2.dist-info/RECORD
