Metadata-Version: 2.1
Name: freq-table
Version: 0.2.2
Summary: Make printable tables using http://radioscanner.ru frequency db
Home-page: https://github.com/snowwm/freq_table
Author: Pavel Andreyev
Author-email: snowwontmelt@gmail.com
License: MIT
Keywords: radio radio-frequency html-table html-generation
Platform: UNKNOWN
Classifier: Development Status :: 3 - Alpha
Classifier: Intended Audience :: Telecommunications Industry
Classifier: Topic :: Printing
Classifier: License :: OSI Approved :: MIT License
Classifier: Programming Language :: Python :: 3
Requires-Python: >=3
Requires-Dist: beautifulsoup4
Requires-Dist: mako
Requires-Dist: pyphen
Requires-Dist: pyyaml
Requires-Dist: requests
